reportbro/__init__.py
reportbro/barcode128.py
reportbro/containers.py
reportbro/context.py
reportbro/data/__init__.py
reportbro/data/logo_watermark.png
reportbro/docelement.py
reportbro/elements.py
reportbro/enums.py
reportbro/errors.py
reportbro/rendering.py
reportbro/reportbro.py
reportbro/structs.py
reportbro/utils.py
reportbro/version.py
reportbro_lib-3.11.3.dist-info/LICENSE
reportbro_lib-3.11.3.dist-info/METADATA
reportbro_lib-3.11.3.dist-info/WHEEL
reportbro_lib-3.11.3.dist-info/RECORD
