Metadata-Version: 2.3
Name: reportbro-lib
Version: 3.11.3
Summary: Generate PDF and Excel reports from visually designed templates
License: AGPL-3.0
Keywords: pdf,excel,report,generate,create,web,template,layout
Author: jobsta
Author-email: alex@reportbro.com
Requires-Python: >=3.9,<4.0
Classifier: Development Status :: 5 - Production/Stable
Classifier: Intended Audience :: Developers
Classifier: License :: OSI Approved :: GNU Affero General Public License v3
Classifier: Programming Language :: Python :: 3
Classifier: Programming Language :: Python :: 3.9
Classifier: Programming Language :: Python :: 3.10
Classifier: Programming Language :: Python :: 3.11
Classifier: Programming Language :: Python :: 3.12
Classifier: Programming Language :: Python :: 3.13
Classifier: Programming Language :: Python :: 3.7
Classifier: Programming Language :: Python :: 3.8
Classifier: Topic :: Software Development :: Libraries :: Python Modules
Requires-Dist: Babel (>=2.14.0,<3.0.0)
Requires-Dist: Pillow (>=10.2.0,<11.0.0)
Requires-Dist: XlsxWriter (>=3.0.3,<4.0.0)
Requires-Dist: python-barcode (>=0.15.1,<0.16.0)
Requires-Dist: qrcode (>=7.4.2,<8.0.0)
Requires-Dist: reportbro-fpdf2 (>=2.8.1,<3.0.0)
Requires-Dist: simpleeval (>=1.0.3,<2.0.0)
Project-URL: Documentation, https://www.reportbro.com/doc/installation
Project-URL: Homepage, https://www.reportbro.com
Project-URL: Repository, https://github.com/jobsta/reportbro-lib
